spinel/__init__.py
spinel/wrapper.py
spinel-1.1.5.dist-info/LICENSE
spinel-1.1.5.dist-info/METADATA
spinel-1.1.5.dist-info/WHEEL
spinel-1.1.5.dist-info/top_level.txt
spinel-1.1.5.dist-info/RECORD
