Metadata-Version: 2.1
Name: spinel
Version: 1.1.5
Summary: A minecraft server wrapper written in python
Home-page: https://github.com/DoubleF3lix/Spinel/
License: UNKNOWN
Platform: UNKNOWN
Classifier: Programming Language :: Python :: 3
Classifier: License :: OSI Approved :: MIT License
Classifier: Operating System :: OS Independent
Requires-Python: >=3.6
